scipackage/__init__.py
scipackage/process.cp312-win_amd64.pyd
scipackage/machinelearningkit/__init__.py
scipackage/machinelearningkit/bestkmeans.cp312-win_amd64.pyd
scipackage/machinelearningkit/binning.cp312-win_amd64.pyd
scipackage/machinelearningkit/correlate.cp312-win_amd64.pyd
scipackage/machinelearningkit/distance.cp312-win_amd64.pyd
scipackage/machinelearningkit/entropy.cp312-win_amd64.pyd
scipackage/machinelearningkit/fourstep.cp312-win_amd64.pyd
scipackage/machinelearningkit/gene.cp312-win_amd64.pyd
scipackage/machinelearningkit/kdtree.cp312-win_amd64.pyd
scipackage/machinelearningkit/linear_regression.cp312-win_amd64.pyd
scipackage/machinelearningkit/louvain.cp312-win_amd64.pyd
scipackage/machinelearningkit/metric.cp312-win_amd64.pyd
scipackage/machinelearningkit/pca.cp312-win_amd64.pyd
scipackage/machinelearningkit/seqsim.cp312-win_amd64.pyd
scipackage/machinelearningkit/similar.cp312-win_amd64.pyd
scipackage/machinelearningkit/trie.cp312-win_amd64.pyd
scipackage/machinelearningkit/weight.cp312-win_amd64.pyd
scipackage/natruelanguagekit/__init__.py
scipackage/natruelanguagekit/entity.cp312-win_amd64.pyd
scipackage/natruelanguagekit/hash.cp312-win_amd64.pyd
scipackage/natruelanguagekit/keyword.cp312-win_amd64.pyd
scipackage/natruelanguagekit/longest_common.cp312-win_amd64.pyd
scipackage/natruelanguagekit/process.cp312-win_amd64.pyd
scipackage/natruelanguagekit/tagging.cp312-win_amd64.pyd
scipackage/natruelanguagekit/tokenize.cp312-win_amd64.pyd
scipackage/natruelanguagekit/topic.cp312-win_amd64.pyd
scipackage/natruelanguagekit/vocab.cp312-win_amd64.pyd
scipackage/neuralnetworkkit/__init__.py
scipackage/neuralnetworkkit/activate.cp312-win_amd64.pyd
scipackage/neuralnetworkkit/attention.cp312-win_amd64.pyd
scipackage/neuralnetworkkit/bert.cp312-win_amd64.pyd
scipackage/neuralnetworkkit/crf.cp312-win_amd64.pyd
scipackage/neuralnetworkkit/dataset.cp312-win_amd64.pyd
scipackage/neuralnetworkkit/dropout.cp312-win_amd64.pyd
scipackage-0.1.4.dist-info/METADATA
scipackage-0.1.4.dist-info/WHEEL
scipackage-0.1.4.dist-info/top_level.txt
scipackage-0.1.4.dist-info/RECORD
