Metadata-Version: 2.1
Name: scipackage
Version: 0.1.4
Home-page: 
Author: 
Author-email: 
Platform: any
